{
  "fill" : {
    "solid" : "display-p3:0.96885,0.99226,1.00000,1.00000"
  },
  "groups" : [
    {
      "layers" : [
        {
          "blend-mode" : "normal",
          "fill" : "none",
          "glass" : true,
          "hidden" : false,
          "image-name" : "AppIcon.png",
          "name" : "AppIcon"
        }
      ],
      "shadow" : {
        "kind" : "neutral",
        "opacity" : 0.5
      },
      "translucency" : {
        "enabled" : true,
        "value" : 0.5
      }
    }
  ],
  "supported-platforms" : {
    "circles" : [
      "watchOS"
    ],
    "squares" : "shared"
  }
}